sageattention/__init__.py
sageattention/attn_qk_int8_block_varlen.py
sageattention/attn_qk_int8_per_block.py
sageattention/attn_qk_int8_per_block_causal.py
sageattention/attn_qk_int8_per_block_causal_varlen.py
sageattention/attn_qk_int8_per_block_h96.py
sageattention/attn_qk_int8_per_block_h96_causal.py
sageattention/core.py
sageattention/quant_per_block.py
sageattention/quant_per_block_hd96.py
sageattention/quant_per_block_varlen.py
sageattention-1.0.5.dist-info/LICENSE
sageattention-1.0.5.dist-info/METADATA
sageattention-1.0.5.dist-info/WHEEL
sageattention-1.0.5.dist-info/top_level.txt
sageattention-1.0.5.dist-info/RECORD
