Metadata-Version: 2.1
Name: sageattention
Version: 1.0.5
Summary: Accurate and efficient 8-bit plug-and-play attention.
Home-page: https://github.com/thu-ml/SageAttention
Author: Jintao Zhang, Haofeng Huang
Author-email: jt-zhang6@gmail.com, huanghf22@mails.tsinghua.edu.cn
License: BSD 3-Clause License
Classifier: Development Status :: 4 - Beta
Classifier: Intended Audience :: Developers
Classifier: Topic :: Software Development :: Libraries :: Python Modules
Classifier: License :: OSI Approved :: BSD License
Classifier: Programming Language :: Python :: 3
Classifier: Programming Language :: Python :: 3.9
Classifier: Programming Language :: Python :: 3.10
Classifier: Programming Language :: Python :: 3.11
Classifier: Operating System :: OS Independent
Requires-Python: >=3.9
License-File: LICENSE
